pluthon/__init__.py
pluthon/compiler_config.py
pluthon/pluthon_ast.py
pluthon/pluthon_functional_data.py
pluthon/pluthon_sugar.py
pluthon/tools.py
pluthon/util.py
pluthon/optimize/__init__.py
pluthon/optimize/constant_index_access_list.py
pluthon/optimize/patterns.py
pluthon/optimize/remove_trace.py
pluthon-1.3.5.dist-info/METADATA
pluthon-1.3.5.dist-info/WHEEL
pluthon-1.3.5.dist-info/top_level.txt
pluthon-1.3.5.dist-info/RECORD
