Metadata-Version: 2.4
Name: pluthon
Version: 1.3.5
Summary: Pluto-like programming language for Cardano Smart Contracts in Python
Home-page: https://github.com/opshin/pluthon
Author: nielstron
Author-email: n.muendler@posteo.de
License: MIT
Keywords: python cardano smart contract blockchain verification haskell
Classifier: Development Status :: 3 - Alpha
Classifier: Intended Audience :: Developers
Classifier: Topic :: Software Development :: Compilers
Classifier: License :: OSI Approved :: MIT License
Classifier: Programming Language :: Python :: 3.9
Classifier: Programming Language :: Python :: 3.10
Classifier: Programming Language :: Python :: 3.11
Classifier: Programming Language :: Python :: 3.12
Classifier: Programming Language :: Python :: 3.13
Requires-Python: >=3
Requires-Dist: uplc>=1.2.0
Requires-Dist: ordered-set>=4.1.0
Dynamic: author
Dynamic: author-email
Dynamic: classifier
Dynamic: description
Dynamic: description-content-type
Dynamic: home-page
Dynamic: keywords
Dynamic: license
Dynamic: requires-dist
Dynamic: requires-python
Dynamic: summary
